HISTORY.rst
LICENSE
MANIFEST.in
README.rst
requirements.txt
setup.cfg
setup.py
django_sabot.egg-info/PKG-INFO
django_sabot.egg-info/SOURCES.txt
django_sabot.egg-info/dependency_links.txt
django_sabot.egg-info/not-zip-safe
django_sabot.egg-info/requires.txt
django_sabot.egg-info/top_level.txt
sabot/__init__.py
sabot/apps.py
sabot/classes.py
sabot/database.py
sabot/producers.py