Metadata-Version: 1.1
Name: django-sabot
Version: 0.1.0
Summary: Provoke predictable errors in your Django projects.
Home-page: https://github.com/rosarior/django-sabot
Author: Roberto Rosario
Author-email: roberto.rosario.gonzalez@gmail.com
License: The MIT License (MIT)
